treeparser/__init__.py
treeparser/treeparser.py
treeparser-0.1.1.dist-info/LICENSE
treeparser-0.1.1.dist-info/METADATA
treeparser-0.1.1.dist-info/WHEEL
treeparser-0.1.1.dist-info/top_level.txt
treeparser-0.1.1.dist-info/RECORD
