Metadata-Version: 2.1
Name: treeparser
Version: 0.1.1
Summary: parsing simple strings into trees
Home-page: https://github.com/robert-lieck/treeparser
Author: Robert Lieck
Author-email: robert.lieck@epfl.ch
License: UNKNOWN
Platform: UNKNOWN
Classifier: Programming Language :: Python :: 3
Classifier: License :: OSI Approved :: GNU General Public License v3 (GPLv3)
Classifier: Operating System :: OS Independent
Requires-Python: >=3.6
